{
  "query": {
    "original": "ACH call",
    "timestamp": "2025-10-31T18:08:13.074Z",
    "language": "English",
    "length": 8,
    "userId": "cli-user"
  },
  "routing": {
    "tier": 1,
    "reasoning": "Kullanıcı 'ACH call' terimini sormuş. Bu, diyabetle ilgili genel bir terim veya kısaltma olabilir. Model, bu tür genel terimleri açıklayabilir. Kullanıcı 'araştır' veya 'derinleş' gibi anahtar kelimeler kullanmadığı için varsayılan T1 tier'ı uygundur.",
    "confidence": 1,
    "model": "",
    "tokens": {
      "input": 0,
      "output": 0
    },
    "cost": 0,
    "latency": 0,
    "timestamp": 1761934094046
  },
  "rounds": [],
  "synthesis": {
    "model": "Gemini 2.5 Flash",
    "temperature": 0,
    "systemPromptVersion": "",
    "sourcesProvided": 0,
    "responseLength": 66,
    "streaming": true,
    "tokens": {
      "input": 0,
      "output": 0
    },
    "cost": 0,
    "latency": 2262,
    "response": "ACH nedir Dilara? Açılımını yazarsan daha iyi yardımcı olabilirim.",
    "finishReason": "",
    "startTime": 1761934093075,
    "endTime": 1761934095337
  },
  "summary": {
    "totalTime": 3266,
    "totalCost": 0.001,
    "totalTokens": {
      "input": 0,
      "output": 0
    },
    "qualityMetrics": {
      "sourceQualityAvg": 0,
      "gapCoverage": 0,
      "journalIFAvg": 0
    },
    "bottlenecks": [
      {
        "stage": "Synthesis",
        "latency": 2262,
        "percentage": null
      }
    ],
    "recommendations": [],
    "tier": "T1",
    "rounds": 0,
    "totalSources": 0
  }
}